geograpy/__init__.py
geograpy/extraction.py
geograpy/labels.py
geograpy/locator.py
geograpy/nominatim.py
geograpy/places.py
geograpy/utils.py
geograpy/wikidata.py
geograpy/data/ISO3166ErrorDictionary.csv
geograpy/data/aliases.csv
geograpy3-0.2.7.dist-info/LICENSE
geograpy3-0.2.7.dist-info/METADATA
geograpy3-0.2.7.dist-info/WHEEL
geograpy3-0.2.7.dist-info/top_level.txt
geograpy3-0.2.7.dist-info/RECORD
