Metadata-Version: 2.1
Name: geograpy3
Version: 0.2.7
Summary: Extract countries, regions and cities from a URL or text
Home-page: https://github.com/somnathrakshit/geograpy3
Download-URL: https://github.com/somnathrakshit/geograpy3
Author: Somnath Rakshit
Author-email: somnath52@gmail.com
License: Apache
Project-URL: Documentation, https://geograpy3.readthedocs.io
Project-URL: Code, https://github.com/somnathrakshit/geograpy3
Project-URL: Issue tracker, https://github.com/somnathrakshit/geograpy3/issues
Classifier: Programming Language :: Python
Classifier: Programming Language :: Python :: 3.7
Classifier: Programming Language :: Python :: 3.8
Classifier: Programming Language :: Python :: 3.9
Classifier: Programming Language :: Python :: 3.10
Classifier: Programming Language :: Python :: 3.11
License-File: LICENSE
Requires-Dist: newspaper3k >=0.2.8
Requires-Dist: nltk >=3.7
Requires-Dist: jellyfish >=0.9.0
Requires-Dist: numpy >=1.21.4
Requires-Dist: pylodstorage >=0.4.7
Requires-Dist: sphinx-rtd-theme
Requires-Dist: scikit-learn >=1.0.2
Requires-Dist: pandas >=1.3.5
Requires-Dist: geopy
Requires-Dist: OSMPythonTools >=0.3.3
